pydata_google_auth/__init__.py
pydata_google_auth/__main__.py
pydata_google_auth/_version.py
pydata_google_auth/_webserver.py
pydata_google_auth/auth.py
pydata_google_auth/cache.py
pydata_google_auth/exceptions.py
pydata_google_auth-1.9.1.dist-info/AUTHORS.md
pydata_google_auth-1.9.1.dist-info/LICENSE.txt
pydata_google_auth-1.9.1.dist-info/METADATA
pydata_google_auth-1.9.1.dist-info/WHEEL
pydata_google_auth-1.9.1.dist-info/top_level.txt
pydata_google_auth-1.9.1.dist-info/RECORD
