Metadata-Version: 2.1
Name: pydata-google-auth
Version: 1.9.1
Summary: PyData helpers for authenticating to Google APIs
Home-page: https://github.com/pydata/pydata-google-auth
Author: The PyData Development Team
Author-email: pydata@googlegroups.com
License: BSD License
Keywords: data
Classifier: Development Status :: 5 - Production/Stable
Classifier: Environment :: Console
Classifier: Intended Audience :: Science/Research
Classifier: Operating System :: OS Independent
Classifier: Programming Language :: Python
Classifier: Programming Language :: Python :: 3.9
Classifier: Programming Language :: Python :: 3.10
Classifier: Programming Language :: Python :: 3.11
Classifier: Programming Language :: Python :: 3.12
Classifier: Programming Language :: Python :: 3.13
Classifier: Topic :: Scientific/Engineering
Classifier: License :: OSI Approved :: BSD License
Requires-Python: >=3.9
License-File: LICENSE.txt
License-File: AUTHORS.md
